<annotation><folder>positives</folder><filename>616.jpg</filename><path>/content/drive/My Drive/DL-projet/NWPU_VHR10_Dataset/positive image set/616.jpg</path><source><database>Unknown</database></source><size><width>946</width><height>533</height><depth>3</depth></size><segmented>0</segmented><object><name>baseball diamond</name><pose>Unspecified</pose><truncated>0</truncated><difficult>0</difficult><bndbox><xmin>555</xmin><ymin>145</ymin><xmax>653</xmax><ymax>214</ymax></bndbox></object><object><name>ground track field</name><pose>Unspecified</pose><truncated>0</truncated><difficult>0</difficult><bndbox><xmin>187</xmin><ymin>179</ymin><xmax>509</xmax><ymax>343</ymax></bndbox></object></annotation>